CRADLE/__init__.py
CRADLE/CalculateCovariates/__init__.py
CRADLE/CalculateCovariates/covariateUtils.cpython-39-darwin.so
CRADLE/CalculateCovariates/covariates.py
CRADLE/CalculateCovariates/taskCovariates.cpython-39-darwin.so
CRADLE/CalculateCovariates/vari.py
CRADLE/CallPeak/__init__.py
CRADLE/CallPeak/calculateRC.py
CRADLE/CallPeak/callPeak.py
CRADLE/CallPeak/vari.py
CRADLE/CorrectBias/__init__.py
CRADLE/CorrectBias/correctBias.py
CRADLE/CorrectBias/covariateUtils.cpython-39-darwin.so
CRADLE/CorrectBias/readCounts.cpython-39-darwin.so
CRADLE/CorrectBias/regression.cpython-39-darwin.so
CRADLE/CorrectBias/taskCovariates.cpython-39-darwin.so
CRADLE/CorrectBias/trainCovariates.cpython-39-darwin.so
CRADLE/CorrectBias/vari.py
CRADLE/CorrectBiasStored/__init__.py
CRADLE/CorrectBiasStored/correctBias.py
CRADLE/CorrectBiasStored/correctReadCounts.py
CRADLE/CorrectBiasStored/regression.py
CRADLE/CorrectBiasStored/vari.py
CRADLE/Normalize/__init__.py
CRADLE/Normalize/normalize.py
CRADLE/correctbiasutils/__init__.py
CRADLE/correctbiasutils/cython.cpython-39-darwin.so
CRADLE/correctbiasutils/vari.py
CRADLE/logging/__init__.py
CRADLE-0.30.0.data/scripts/cradle
CRADLE-0.30.0.dist-info/LICENSE
CRADLE-0.30.0.dist-info/METADATA
CRADLE-0.30.0.dist-info/WHEEL
CRADLE-0.30.0.dist-info/top_level.txt
CRADLE-0.30.0.dist-info/RECORD
