Metadata-Version: 2.1
Name: CRADLE
Version: 0.30.0
Summary: Correct Read Counts and Analysis of Differently Expressed Regions
Home-page: https://github.com/ReddyLab/CRADLE
Author: Young-Sook Kim
Author-email: kys91240@gmail.com
Classifier: Programming Language :: Python :: 3.7
Classifier: License :: OSI Approved :: MIT License
License-File: LICENSE
Requires-Dist: numpy >=1.14.3
Requires-Dist: argparse >=1.1
Requires-Dist: py2bit >=0.3.0
Requires-Dist: pyBigWig >=0.3.11
Requires-Dist: statsmodels >=0.8.0
Requires-Dist: scipy >=1.0.1
Requires-Dist: matplotlib >=1.5.3
Requires-Dist: h5py >=2.6.0
Requires-Dist: Cython >=0.24.1
